<annotation>
	<folder>OnePersonPositivLeft</folder>
	<filename>2450_einePersonPositiv.png</filename>
	<path>C:\Users\Sternenhimmel\Documents\TestBilder\Positiv\OnePersonPositivLeft\2450_einePersonPositiv.png</path>
	<source>
		<database>Unknown</database>
	</source>
	<size>
		<width>640</width>
		<height>480</height>
		<depth>1</depth>
	</size>
	<segmented>0</segmented>
	<object>
		<name>hand</name>
		<pose>Unspecified</pose>
		<truncated>0</truncated>
		<difficult>0</difficult>
		<bndbox>
			<xmin>226</xmin>
			<ymin>36</ymin>
			<xmax>273</xmax>
			<ymax>95</ymax>
		</bndbox>
	</object>
	<object>
		<name>hand</name>
		<pose>Unspecified</pose>
		<truncated>0</truncated>
		<difficult>0</difficult>
		<bndbox>
			<xmin>431</xmin>
			<ymin>52</ymin>
			<xmax>472</xmax>
			<ymax>119</ymax>
		</bndbox>
	</object>
	<object>
		<name>head</name>
		<pose>Unspecified</pose>
		<truncated>0</truncated>
		<difficult>0</difficult>
		<bndbox>
			<xmin>300</xmin>
			<ymin>165</ymin>
			<xmax>354</xmax>
			<ymax>218</ymax>
		</bndbox>
	</object>
	<object>
		<name>person</name>
		<pose>Unspecified</pose>
		<truncated>1</truncated>
		<difficult>0</difficult>
		<bndbox>
			<xmin>226</xmin>
			<ymin>36</ymin>
			<xmax>473</xmax>
			<ymax>480</ymax>
		</bndbox>
	</object>
</annotation>
